{
  "resourceType": "StructureDefinition",
  "id": "aktin-pr-vitalsigns-schmerz",
  "url": "http://aktin.org/fhir/StructureDefinition/aktin-pr-vitalsigns-schmerz",
  "version": "2025.0.3-ci",
  "name": "AKTIN_PR_vitalsigns_schmerz",
  "title": "Erste Schmerzmessung",
  "status": "active",
  "experimental": true,
  "date": "2025-06-12",
  "publisher": "AKTIN e.V.",
  "contact": [
    {
      "telecom": [
        {
          "system": "url",
          "value": "https://www.aktin.org"
        }
      ]
    }
  ],
  "description": "Erste Schmerzmessung mit NRS oder VAS",
  "purpose": "**Hinweis**: Dieses Profil ist nicht dazu gedacht, implementiert zu werden. Es macht deutlich, welche (zusätzlichen) AKTIN-spezifischen Eigenschaften ein existierendes Profil (bekannter Baustein 'Vitalparameter/Scores') zu diesem Typ haben muss und welche Constraints gelten. Es dient dem Aufzeigen der semantischen Annotationen des zugrundeliegenden Konzepts und optional der Bindung der Valusets an Antwort-Auswahllisten, kodierten Zusatzinformationen und Maßeinheiten. Das Profil wird nach Festlegung der bekannten Bausteine als formale Restriktion profilert.",
  "fhirVersion": "4.0.1",
  "kind": "resource",
  "abstract": true,
  "type": "Observation",
  "baseDefinition": "http://hl7.org/fhir/StructureDefinition/Observation",
  "derivation": "constraint",
  "differential": {
    "element": [
      {
        "id": "Observation",
        "path": "Observation",
        "definition": "Erste Schmerzmessung mit NRS oder VAS",
        "comment": "Profil ist Übersicht über AKTIN-spezifische Gegebenheiten"
      },
      {
        "id": "Observation.identifier",
        "path": "Observation.identifier",
        "mustSupport": true
      },
      {
        "id": "Observation.category",
        "path": "Observation.category",
        "slicing": {
          "discriminator": [
            {
              "type": "pattern",
              "path": "$this"
            }
          ],
          "rules": "open"
        },
        "min": 1
      },
      {
        "id": "Observation.category:thisCat",
        "path": "Observation.category",
        "sliceName": "thisCat",
        "min": 1,
        "max": "1",
        "patternCodeableConcept": {
          "coding": [
            {
              "code": "vital-signs",
              "system": "http://terminology.hl7.org/CodeSystem/observation-category",
              "display": "Vital Signs"
            }
          ]
        }
      },
      {
        "id": "Observation.category:thisCat.text",
        "path": "Observation.category.text",
        "patternString": "Vital Signs"
      },
      {
        "id": "Observation.code",
        "path": "Observation.code",
        "mustSupport": true
      },
      {
        "id": "Observation.code.coding",
        "path": "Observation.code.coding",
        "slicing": {
          "discriminator": [
            {
              "type": "pattern",
              "path": "$this"
            }
          ],
          "rules": "open"
        },
        "min": 2,
        "mustSupport": true
      },
      {
        "id": "Observation.code.coding:SNOMED-CT",
        "path": "Observation.code.coding",
        "sliceName": "SNOMED-CT",
        "min": 1,
        "max": "1",
        "patternCoding": {
          "code": "225908003",
          "system": "http://snomed.info/sct",
          "display": "Pain score (observable entity)"
        },
        "mustSupport": true
      },
      {
        "id": "Observation.code.coding:LOINC",
        "path": "Observation.code.coding",
        "sliceName": "LOINC",
        "min": 1,
        "max": "1",
        "patternCoding": {
          "code": "72514-3",
          "system": "http://loinc.org",
          "display": "Pain severity - 0-10 verbal numeric rating [Score] - Reported"
        },
        "mustSupport": true
      },
      {
        "id": "Observation.code.text",
        "path": "Observation.code.text",
        "patternString": "Schmerz"
      },
      {
        "id": "Observation.subject",
        "path": "Observation.subject",
        "min": 1,
        "type": [
          {
            "code": "Reference",
            "targetProfile": [
              "http://hl7.org/fhir/StructureDefinition/Patient"
            ]
          }
        ],
        "mustSupport": true
      },
      {
        "id": "Observation.effective[x]",
        "path": "Observation.effective[x]",
        "min": 1,
        "type": [
          {
            "code": "dateTime"
          }
        ],
        "mustSupport": true
      },
      {
        "id": "Observation.value[x]",
        "path": "Observation.value[x]",
        "type": [
          {
            "code": "Quantity"
          }
        ],
        "patternQuantity": {
          "code": "{score}",
          "system": "http://unitsofmeasure.org"
        },
        "mustSupport": true
      }
    ]
  }
}
