{
  "resourceType": "ValueSet",
  "status": "active",
  "name": "Substance_used",
  "id": "aktin-vs-substances-used",
  "title": "Substanz-Einfluss",
  "description": "Patient unter Substanz-Einfluss?",
  "url": "http://aktin.org/fhir/ValueSet/aktin-vs-substances-used",
  "publisher": "AKTIN e.V.",
  "contact": [
    {
      "telecom": [
        {
          "system": "url",
          "value": "https://www.aktin.org"
        }
      ]
    }
  ],
  "meta": {
    "profile": [
      "http://hl7.org/fhir/StructureDefinition/shareablevalueset"
    ]
  },
  "experimental": false,
  "compose": {
    "include": [
      {
        "system": "http://loinc.org",
        "concept": [
          {
            "code": "LA28145-3",
            "display": "Patient is not influenced by substance use"
          },
          {
            "code": "LA28144-6",
            "display": "Unknown substance"
          },
          {
            "code": "LA28139-6",
            "display": "Alcohol"
          },
          {
            "code": "LA22650-8",
            "display": "Medication"
          },
          {
            "code": "LA28141-2",
            "display": "Illegal drug"
          },
          {
            "code": "LA28142-0",
            "display": "Multiple substances"
          },
          {
            "code": "LA46-8",
            "display": "Other"
          }
        ]
      }
    ]
  }
}
